MaaAgentBinary/LICENSE
MaaAgentBinary/README.md
MaaAgentBinary/maatouch/universal/maatouch
MaaAgentBinary/minicap/arm64-v8a/bin/minicap
MaaAgentBinary/minicap/arm64-v8a/bin/minicap-nopie
MaaAgentBinary/minicap/arm64-v8a/lib/android-21/minicap.so
MaaAgentBinary/minicap/arm64-v8a/lib/android-22/minicap.so
MaaAgentBinary/minicap/arm64-v8a/lib/android-23/minicap.so
MaaAgentBinary/minicap/arm64-v8a/lib/android-24/minicap.so
MaaAgentBinary/minicap/arm64-v8a/lib/android-25/minicap.so
MaaAgentBinary/minicap/arm64-v8a/lib/android-26/minicap.so
MaaAgentBinary/minicap/arm64-v8a/lib/android-27/minicap.so
MaaAgentBinary/minicap/arm64-v8a/lib/android-28/minicap.so
MaaAgentBinary/minicap/arm64-v8a/lib/android-29/minicap
MaaAgentBinary/minicap/arm64-v8a/lib/android-29/minicap-nopie
MaaAgentBinary/minicap/arm64-v8a/lib/android-29/minicap.so
MaaAgentBinary/minicap/arm64-v8a/lib/android-30/minicap.so
MaaAgentBinary/minicap/arm64-v8a/lib/android-31/minicap.so
MaaAgentBinary/minicap/armeabi-v7a/bin/minicap
MaaAgentBinary/minicap/armeabi-v7a/bin/minicap-nopie
MaaAgentBinary/minicap/armeabi-v7a/lib/android-10/minicap.so
MaaAgentBinary/minicap/armeabi-v7a/lib/android-14/minicap.so
MaaAgentBinary/minicap/armeabi-v7a/lib/android-15/minicap.so
MaaAgentBinary/minicap/armeabi-v7a/lib/android-16/minicap.so
MaaAgentBinary/minicap/armeabi-v7a/lib/android-17/minicap.so
MaaAgentBinary/minicap/armeabi-v7a/lib/android-18/minicap.so
MaaAgentBinary/minicap/armeabi-v7a/lib/android-19/minicap.so
MaaAgentBinary/minicap/armeabi-v7a/lib/android-21/minicap.so
MaaAgentBinary/minicap/armeabi-v7a/lib/android-22/minicap.so
MaaAgentBinary/minicap/armeabi-v7a/lib/android-23/minicap.so
MaaAgentBinary/minicap/armeabi-v7a/lib/android-24/minicap.so
MaaAgentBinary/minicap/armeabi-v7a/lib/android-25/minicap.so
MaaAgentBinary/minicap/armeabi-v7a/lib/android-26/minicap.so
MaaAgentBinary/minicap/armeabi-v7a/lib/android-27/minicap.so
MaaAgentBinary/minicap/armeabi-v7a/lib/android-28/minicap.so
MaaAgentBinary-1.0.1.dist-info/LICENSE
MaaAgentBinary-1.0.1.dist-info/METADATA
MaaAgentBinary-1.0.1.dist-info/WHEEL
MaaAgentBinary-1.0.1.dist-info/top_level.txt
MaaAgentBinary-1.0.1.dist-info/RECORD
