Metadata-Version: 2.1
Name: MaaAgentBinary
Version: 1.0.1
Summary: AgentBinary for MaaFw
Author: MaaXYZ
Project-URL: Homepage, https://github.com/MaaXYZ/MaaAgentBinary
License-File: LICENSE
